llm_guard/__init__.py
llm_guard/evaluate.py
llm_guard/exception.py
llm_guard/model.py
llm_guard/transformers_helpers.py
llm_guard/util.py
llm_guard/vault.py
llm_guard/version.py
llm_guard/input_scanners/__init__.py
llm_guard/input_scanners/anonymize.py
llm_guard/input_scanners/ban_code.py
llm_guard/input_scanners/ban_competitors.py
llm_guard/input_scanners/ban_substrings.py
llm_guard/input_scanners/ban_topics.py
llm_guard/input_scanners/base.py
llm_guard/input_scanners/code.py
llm_guard/input_scanners/gibberish.py
llm_guard/input_scanners/invisible_text.py
llm_guard/input_scanners/language.py
llm_guard/input_scanners/prompt_injection.py
llm_guard/input_scanners/regex.py
llm_guard/input_scanners/secrets.py
llm_guard/input_scanners/sentiment.py
llm_guard/input_scanners/token_limit.py
llm_guard/input_scanners/toxicity.py
llm_guard/input_scanners/util.py
llm_guard/input_scanners/anonymize_helpers/__init__.py
llm_guard/input_scanners/anonymize_helpers/analyzer.py
llm_guard/input_scanners/anonymize_helpers/faker.py
llm_guard/input_scanners/anonymize_helpers/ner_mapping.py
llm_guard/input_scanners/anonymize_helpers/regex_patterns.py
llm_guard/input_scanners/anonymize_helpers/transformers_recognizer.py
llm_guard/input_scanners/anonymize_helpers/predefined_recognizers/__init__.py
llm_guard/input_scanners/anonymize_helpers/predefined_recognizers/phone_recognizer.py
llm_guard/input_scanners/anonymize_helpers/predefined_recognizers/zh/__init__.py
llm_guard/input_scanners/anonymize_helpers/predefined_recognizers/zh/crypto_recognizer.py
llm_guard/input_scanners/anonymize_helpers/predefined_recognizers/zh/custom_pattern_recognizer.py
llm_guard/input_scanners/anonymize_helpers/predefined_recognizers/zh/email_recognizer.py
llm_guard/input_scanners/anonymize_helpers/predefined_recognizers/zh/ip_recognizer.py
llm_guard/input_scanners/secrets_plugins/__init__.py
llm_guard/input_scanners/secrets_plugins/adafruit.py
llm_guard/input_scanners/secrets_plugins/adobe.py
llm_guard-0.3.15.dist-info/LICENSE
llm_guard-0.3.15.dist-info/METADATA
llm_guard-0.3.15.dist-info/WHEEL
llm_guard-0.3.15.dist-info/top_level.txt
llm_guard-0.3.15.dist-info/RECORD
