Metadata-Version: 2.1
Name: llm-guard
Version: 0.3.15
Summary: LLM-Guard is a comprehensive tool designed to fortify the security of Large Language Models (LLMs). By offering sanitization, detection of harmful language, prevention of data leakage, and resistance against prompt injection attacks, LLM-Guard ensures that your interactions with LLMs remain safe and secure.
Author-email: Protect AI <community@protectai.com>
License: The MIT License (MIT)
Project-URL: homepage, https://github.com/protectai/llm-guard
Project-URL: documentation, https://llm-guard.com/
Project-URL: repository, https://github.com/protectai/llm-guard
Project-URL: issues, https://github.com/protectai/llm-guard/issues
Project-URL: changelog, https://llm-guard.com/changelog/
Keywords: llm,language model,security,adversarial attacks,prompt injection,prompt leakage,PII detection,self-hardening,firewall
Classifier: Development Status :: 4 - Beta
Classifier: Intended Audience :: Developers
Classifier: License :: OSI Approved :: MIT License
Classifier: Programming Language :: Python :: 3
Classifier: Programming Language :: Python :: 3.9
Classifier: Programming Language :: Python :: 3.10
Classifier: Programming Language :: Python :: 3.11
Requires-Python: <3.13,>=3.9
License-File: LICENSE
Requires-Dist: bc-detect-secrets==1.5.15
Requires-Dist: faker<28,>=26.0.0
Requires-Dist: fuzzysearch<0.9,>=0.7
Requires-Dist: json-repair<0.29,>=0.25.2
Requires-Dist: nltk<4,>=3.9.1
Requires-Dist: presidio-analyzer==2.2.354
Requires-Dist: presidio-anonymizer==2.2.354
Requires-Dist: regex==2024.7.24
Requires-Dist: tiktoken<0.8,>=0.5
Requires-Dist: torch>=2.4.0
Requires-Dist: transformers>=4.43.4
Requires-Dist: structlog>=24
Requires-Dist: oldest-supported-numpy
Provides-Extra: dev
Requires-Dist: llm-guard[docs-dev]; extra == "dev"
Requires-Dist: autoflake<3,>=2; extra == "dev"
Requires-Dist: pytest<9,>=8.0.0; extra == "dev"
Requires-Dist: pytest-cov<6,>=5.0.0; extra == "dev"
Requires-Dist: pre-commit<4,>=3.8; extra == "dev"
Requires-Dist: pyright~=1.1.376; extra == "dev"
Requires-Dist: ruff<0.7.0,>=0.6.1; extra == "dev"
Provides-Extra: docs-dev
Requires-Dist: mkdocs<2,>=1.6; extra == "docs-dev"
Requires-Dist: mkdocs-autorefs==1.1.0; extra == "docs-dev"
Requires-Dist: mkdocs-git-revision-date-localized-plugin>=1.2; extra == "docs-dev"
Requires-Dist: mkdocs-jupyter>=0.24; extra == "docs-dev"
Requires-Dist: mkdocs-material>=9.5; extra == "docs-dev"
Requires-Dist: mkdocs-material-extensions>=1.3; extra == "docs-dev"
Requires-Dist: mkdocs-swagger-ui-tag>=0.6; extra == "docs-dev"
Provides-Extra: onnxruntime
Requires-Dist: optimum[onnxruntime]>=1.21; extra == "onnxruntime"
Provides-Extra: onnxruntime-gpu
Requires-Dist: optimum[onnxruntime-gpu]>=1.21; extra == "onnxruntime-gpu"
